{"problem": {"type": "puboi", "date": "18:12:03 01/10/24 CET", "generator": "https://gitlab.com/verel/pubo-importance-benchmark/src/generator/puboi_generator.py", "author": "LEC group/LISIC/ULCO", "seed":1103, "n":64, "size":[16, 48], "degree":[1.0, 1.0], "m":101, "factor":1.0, "p_function":[0.25, 0.25, 0.25, 0.25], "typeWeight":0, "shift":true, "objective": "min", "bound": -342, "terms": [{"w":-2,"ids":[9,23]},{"w":2,"ids":[23,27]},{"w":-1,"ids":[27,36]},{"w":-2,"ids":[9,36]},{"w":-2,"ids":[6,28]},{"w":2,"ids":[28,41]},{"w":-1,"ids":[17,41]},{"w":-2,"ids":[6,17]},{"w":1,"ids":[2,7]},{"w":-2,"ids":[2,21]},{"w":1,"ids":[21,26]},{"w":2,"ids":[7,26]},{"w":-2,"ids":[6,8]},{"w":-1,"ids":[8,16]},{"w":-1,"ids":[16,56]},{"w":2,"ids":[6,56]},{"w":-2,"ids":[0,7]},{"w":2,"ids":[7,12]},{"w":-1,"ids":[6,12]},{"w":-4,"ids":[0,6]},{"w":-2,"ids":[2,8]},{"w":1,"ids":[1,13]},{"w":2,"ids":[2,13]},{"w":2,"ids":[6,59]},{"w":1,"ids":[22,59]},{"w":-1,"ids":[15,22]},{"w":3,"ids":[8,10]},{"w":1,"ids":[4,10]},{"w":-1,"ids":[4,51]},{"w":-2,"ids":[8,51]},{"w":2,"ids":[2,3]},{"w":2,"ids":[2,34]},{"w":1,"ids":[24,34]},{"w":-2,"ids":[3,24]},{"w":2,"ids":[2,4]},{"w":-2,"ids":[1,4]},{"w":-1,"ids":[1,53]},{"w":2,"ids":[2,53]},{"w":1,"ids":[3,8]},{"w":-1,"ids":[1,56]},{"w":-1,"ids":[3,56]},{"w":2,"ids":[1,5]},{"w":2,"ids":[5,61]},{"w":1,"ids":[18,61]},{"w":1,"ids":[1,18]},{"w":2,"ids":[7,13]},{"w":-2,"ids":[13,40]},{"w":1,"ids":[40,56]},{"w":2,"ids":[7,56]},{"w":-3,"ids":[3,14]},{"w":-2,"ids":[3,10]},{"w":1,"ids":[10,63]},{"w":-2,"ids":[14,63]},{"w":-1,"ids":[8,23]},{"w":2,"ids":[23,51]},{"w":-1,"ids":[45,51]},{"w":-2,"ids":[8,45]},{"w":-2,"ids":[11,15]},{"w":-2,"ids":[10,15]},{"w":1,"ids":[10,35]},{"w":-2,"ids":[11,35]},{"w":2,"ids":[13,34]},{"w":2,"ids":[34,49]},{"w":-1,"ids":[49,60]},{"w":2,"ids":[13,60]},{"w":-2,"ids":[5,37]},{"w":-1,"ids":[17,37]},{"w":-2,"ids":[1,17]},{"w":2,"ids":[1,2]},{"w":-2,"ids":[2,5]},{"w":2,"ids":[1,45]},{"w":4,"ids":[1,9]},{"w":2,"ids":[7,9]},{"w":1,"ids":[0,1]},{"w":3,"ids":[3,5]},{"w":2,"ids":[5,54]},{"w":1,"ids":[35,54]},{"w":-1,"ids":[3,35]},{"w":2,"ids":[5,15]},{"w":2,"ids":[13,15]},{"w":-1,"ids":[13,16]},{"w":1,"ids":[5,16]},{"w":2,"ids":[4,7]},{"w":2,"ids":[7,23]},{"w":1,"ids":[23,50]},{"w":-1,"ids":[4,50]},{"w":2,"ids":[15,45]},{"w":2,"ids":[27,45]},{"w":-1,"ids":[27,34]},{"w":1,"ids":[15,34]},{"w":1,"ids":[14,15]},{"w":2,"ids":[14,18]},{"w":1,"ids":[18,28]},{"w":-1,"ids":[15,28]},{"w":-2,"ids":[1,15]},{"w":-2,"ids":[1,60]},{"w":1,"ids":[25,60]},{"w":-1,"ids":[15,25]},{"w":-3,"ids":[9,10]},{"w":-2,"ids":[10,22]},{"w":-1,"ids":[16,22]},{"w":1,"ids":[9,16]},{"w":-1,"ids":[1,14]},{"w":-2,"ids":[1,28]},{"w":1,"ids":[28,40]},{"w":-1,"ids":[14,40]},{"w":-2,"ids":[15,56]},{"w":-2,"ids":[53,56]},{"w":1,"ids":[44,53]},{"w":-1,"ids":[15,44]},{"w":2,"ids":[11,14]},{"w":4,"ids":[8,14]},{"w":-1,"ids":[11,16]},{"w":-1,"ids":[5,14]},{"w":-2,"ids":[7,14]},{"w":-1,"ids":[7,21]},{"w":1,"ids":[5,21]},{"w":-2,"ids":[10,57]},{"w":2,"ids":[51,57]},{"w":1,"ids":[44,51]},{"w":1,"ids":[10,44]},{"w":2,"ids":[1,11]},{"w":-1,"ids":[11,32]},{"w":1,"ids":[9,32]},{"w":2,"ids":[12,49]},{"w":2,"ids":[22,49]},{"w":1,"ids":[22,32]},{"w":-1,"ids":[12,32]},{"w":3,"ids":[0,10]},{"w":-2,"ids":[6,55]},{"w":-1,"ids":[10,55]},{"w":-2,"ids":[2,42]},{"w":1,"ids":[42,57]},{"w":-1,"ids":[4,57]},{"w":1,"ids":[7,29]},{"w":-2,"ids":[29,34]},{"w":-1,"ids":[34,44]},{"w":-1,"ids":[7,44]},{"w":3,"ids":[7,32]},{"w":1,"ids":[24,32]},{"w":-1,"ids":[24,38]},{"w":1,"ids":[7,38]},{"w":-2,"ids":[7,41]},{"w":2,"ids":[25,41]},{"w":1,"ids":[25,46]},{"w":1,"ids":[7,46]},{"w":4,"ids":[11,12]},{"w":-2,"ids":[12,51]},{"w":1,"ids":[51,61]},{"w":1,"ids":[11,61]},{"w":2,"ids":[9,33]},{"w":-2,"ids":[26,33]},{"w":-1,"ids":[26,61]},{"w":-2,"ids":[9,61]},{"w":1,"ids":[12,15]},{"w":-2,"ids":[15,23]},{"w":1,"ids":[23,36]},{"w":1,"ids":[12,36]},{"w":-3,"ids":[0,9]},{"w":2,"ids":[9,52]},{"w":-1,"ids":[30,52]},{"w":-1,"ids":[0,30]},{"w":-2,"ids":[2,6]},{"w":-2,"ids":[6,48]},{"w":-1,"ids":[48,55]},{"w":1,"ids":[2,55]},{"w":-2,"ids":[8,31]},{"w":-1,"ids":[31,38]},{"w":-1,"ids":[14,38]},{"w":-1,"ids":[4,9]},{"w":-2,"ids":[4,12]},{"w":-1,"ids":[12,37]},{"w":1,"ids":[9,37]},{"w":-2,"ids":[4,6]},{"w":2,"ids":[4,24]},{"w":1,"ids":[24,47]},{"w":1,"ids":[6,47]},{"w":1,"ids":[1,7]},{"w":2,"ids":[1,12]},{"w":1,"ids":[12,52]},{"w":-1,"ids":[7,52]},{"w":-2,"ids":[1,50]},{"w":-2,"ids":[19,50]},{"w":1,"ids":[19,48]},{"w":-1,"ids":[1,48]},{"w":-1,"ids":[0,8]},{"w":-1,"ids":[0,39]},{"w":-1,"ids":[30,39]},{"w":2,"ids":[8,30]},{"w":2,"ids":[3,13]},{"w":-1,"ids":[13,57]},{"w":1,"ids":[16,57]},{"w":2,"ids":[3,16]},{"w":2,"ids":[0,14]},{"w":-1,"ids":[3,28]},{"w":-2,"ids":[0,28]},{"w":1,"ids":[6,34]},{"w":-1,"ids":[32,34]},{"w":1,"ids":[32,38]},{"w":2,"ids":[6,38]},{"w":-2,"ids":[7,58]},{"w":1,"ids":[10,34]},{"w":-1,"ids":[25,34]},{"w":3,"ids":[8,25]},{"w":1,"ids":[0,55]},{"w":2,"ids":[9,55]},{"w":3,"ids":[9,14]},{"w":-3,"ids":[6,9]},{"w":1,"ids":[6,10]},{"w":1,"ids":[1,6]},{"w":-1,"ids":[9,12]},{"w":1,"ids":[12,59]},{"w":1,"ids":[45,59]},{"w":2,"ids":[9,45]},{"w":1,"ids":[9,15]},{"w":1,"ids":[4,15]},{"w":-1,"ids":[14,57]},{"w":1,"ids":[0,4]},{"w":-2,"ids":[10,51]},{"w":-2,"ids":[0,24]},{"w":1,"ids":[4,14]},{"w":-1,"ids":[14,32]},{"w":-1,"ids":[32,37]},{"w":-2,"ids":[4,37]},{"w":-1,"ids":[6,7]},{"w":-1,"ids":[1,32]},{"w":-1,"ids":[5,12]},{"w":1,"ids":[5,40]},{"w":2,"ids":[11,40]},{"w":1,"ids":[13,14]},{"w":1,"ids":[14,61]},{"w":-2,"ids":[3,61]},{"w":1,"ids":[8,11]},{"w":2,"ids":[11,43]},{"w":1,"ids":[9,25]},{"w":-1,"ids":[20,25]},{"w":1,"ids":[20,51]},{"w":2,"ids":[9,51]},{"w":1,"ids":[11,19]},{"w":2,"ids":[15,19]},{"w":1,"ids":[8,13]},{"w":1,"ids":[13,18]},{"w":1,"ids":[18,37]},{"w":-2,"ids":[8,37]},{"w":-1,"ids":[50,58]},{"w":-1,"ids":[47,50]},{"w":1,"ids":[18,47]},{"w":1,"ids":[6,14]},{"w":1,"ids":[15,53]},{"w":-1,"ids":[6,53]},{"w":-1,"ids":[17,55]},{"w":1,"ids":[17,43]},{"w":-1,"ids":[6,43]},{"w":1,"ids":[7,11]},{"w":-1,"ids":[11,23]},{"w":1,"ids":[7,43]},{"w":1,"ids":[9,54]},{"w":-1,"ids":[6,54]},{"w":1,"ids":[5,38]},{"w":-1,"ids":[27,38]},{"w":1,"ids":[27,49]},{"w":2,"ids":[5,49]},{"w":1,"ids":[40,59]},{"w":1,"ids":[7,40]},{"w":1,"ids":[9,43]},{"w":1,"ids":[1,43]},{"w":1,"ids":[1,51]},{"w":-1,"ids":[19,51]},{"w":1,"ids":[14,19]},{"w":1,"ids":[0,18]},{"w":1,"ids":[18,42]},{"w":-1,"ids":[14,42]},{"w":-1,"ids":[7,62]},{"w":-1,"ids":[9,62]},{"w":1,"ids":[9,22]},{"w":1,"ids":[14,20]},{"w":1,"ids":[0,20]},{"w":-1,"ids":[5,41]},{"w":-1,"ids":[41,49]},{"w":1,"ids":[49,57]},{"w":-1,"ids":[5,57]},{"w":1,"ids":[3,11]},{"w":1,"ids":[11,25]},{"w":-1,"ids":[0,62]},{"w":1,"ids":[49,62]},{"w":-1,"ids":[4,17]},{"w":1,"ids":[17,52]},{"w":-1,"ids":[51,52]},{"w":1,"ids":[37,50]},{"w":1,"ids":[43,50]},{"w":1,"ids":[19,43]},{"w":-1,"ids":[19,37]},{"w":1,"ids":[9,59]},{"w":1,"ids":[28,29]},{"w":1,"ids":[9,28]},{"w":-1,"ids":[10,13]},{"w":1,"ids":[5,20]},{"w":1,"ids":[13,20]},{"w":1,"ids":[10,42]},{"w":-1,"ids":[42,48]},{"w":1,"ids":[0,48]},{"w":-1,"ids":[54,61]},{"w":-1,"ids":[40,54]},{"w":1,"ids":[9,40]},{"w":1,"ids":[9,42]},{"w":1,"ids":[27,42]},{"w":1,"ids":[27,56]},{"w":-1,"ids":[9,56]},{"w":1,"ids":[1,40]},{"w":1,"ids":[25,40]},{"w":-1,"ids":[19,25]},{"w":1,"ids":[1,19]},{"w":-1,"ids":[4,5]},{"w":1,"ids":[12,13]},{"w":1,"ids":[12,26]},{"w":1,"ids":[5,26]},{"w":-1,"ids":[10,11]},{"w":1,"ids":[0,53]},{"w":1,"ids":[11,53]},{"w":-1,"ids":[13,56]},{"w":1,"ids":[5,6]},{"w":1,"ids":[45,57]},{"w":1,"ids":[6,57]}]}}
